pyaeneas/__init__.py
pyaeneas/client.py
pyaeneas/exceptions.py
pyaeneas-0.2.dist-info/LICENSE.txt
pyaeneas-0.2.dist-info/METADATA
pyaeneas-0.2.dist-info/WHEEL
pyaeneas-0.2.dist-info/top_level.txt
pyaeneas-0.2.dist-info/RECORD
