Metadata-Version: 2.1
Name: pyaeneas
Version: 0.2
Summary: Aeneas fullnode API Python client
Home-page: https://github.com/AverHLV/pyaeneas
Author: Andrii Matiiash
Author-email: andmati743@gmail.com
License: MIT
Download-URL: https://github.com/AverHLV/pyaeneas/archive/0.2.tar.gz
Keywords: ASYNC,AENEAS,CLIENT,BLOCKCHAIN
Platform: UNKNOWN
Classifier: Development Status :: 3 - Alpha
Classifier: Intended Audience :: Developers
Classifier: Topic :: Software Development :: Libraries
Classifier: License :: OSI Approved :: MIT License
Classifier: Programming Language :: Python :: 3.5
Classifier: Programming Language :: Python :: 3.6
Classifier: Programming Language :: Python :: 3.7
Requires-Dist: aiohttp
